notion/__init__.py
notion/notion.py
python_notion-0.0.2.dist-info/AUTHORS.rst
python_notion-0.0.2.dist-info/LICENSE
python_notion-0.0.2.dist-info/METADATA
python_notion-0.0.2.dist-info/WHEEL
python_notion-0.0.2.dist-info/top_level.txt
python_notion-0.0.2.dist-info/RECORD
